otoe/__init__.py
otoe/config.py
otoe/dialogs.py
otoe/espanso.py
otoe/exceptions.py
otoe/obsidian.py
otoe/parsers.py
otoe/tests/__init__.py
otoe/tests/test_md.py
otoe/tests/test_otoe.py
tests/__init__.py
tests/test_md.py
tests/test_otoe.py
otoe-0.0.9.dist-info/METADATA
otoe-0.0.9.dist-info/WHEEL
otoe-0.0.9.dist-info/entry_points.txt
otoe-0.0.9.dist-info/top_level.txt
otoe-0.0.9.dist-info/RECORD
