Metadata-Version: 2.1
Name: otoe
Version: 0.0.9
Summary: Sort of a UI for espanso configs.
Author: Yakov Varnaev
Classifier: Programming Language :: Python :: 3
Classifier: License :: OSI Approved :: MIT License
Classifier: Operating System :: OS Independent
Requires-Python: >=3.11
Requires-Dist: pyyaml
